spectra/__init__.py
spectra/client.py
spectra/main.py
spectra/py.typed
spectra/scanner.py
spectra_cli-0.1.2.dist-info/licenses/LICENSE
spectra_cli-0.1.2.dist-info/METADATA
spectra_cli-0.1.2.dist-info/WHEEL
spectra_cli-0.1.2.dist-info/entry_points.txt
spectra_cli-0.1.2.dist-info/top_level.txt
spectra_cli-0.1.2.dist-info/RECORD
