Metadata-Version: 2.4
Name: spectra-cli
Version: 0.1.2
Summary: Generate production-ready DevOps files for your projects using AI
Home-page: https://github.com/yourusername/spectra-cli
Author: Spectra Team
License-Expression: MIT
Project-URL: Homepage, https://github.com/hamzaparvez-dev/spectra-cli
Project-URL: Documentation, https://github.com/hamzaparvez-dev/spectra-cli#readme
Project-URL: Repository, https://github.com/hamzaparvez-dev/spectra-cli
Project-URL: Issues, https://github.com/hamzaparvez-dev/spectra-cli/issues
Keywords: devops,docker,ci-cd,cli,automation
Classifier: Development Status :: 4 - Beta
Classifier: Intended Audience :: Developers
Classifier: Programming Language :: Python :: 3
Classifier: Programming Language :: Python :: 3.8
Classifier: Programming Language :: Python :: 3.9
Classifier: Programming Language :: Python :: 3.10
Classifier: Programming Language :: Python :: 3.11
Classifier: Programming Language :: Python :: 3.12
Classifier: Topic :: Software Development :: Build Tools
Classifier: Topic :: System :: Systems Administration
Requires-Python: >=3.8
License-File: LICENSE
Requires-Dist: typer[all]>=0.9.0
Requires-Dist: httpx>=0.26.0
Requires-Dist: rich>=13.7.0
Requires-Dist: fastapi>=0.115.0
Requires-Dist: pydantic>=2.9.0
Requires-Dist: uvicorn[standard]>=0.32.0
Requires-Dist: redis>=5.2.0
Requires-Dist: mangum>=0.17.0
Dynamic: home-page
Dynamic: license-file
Dynamic: requires-python
